cheutils/__init__.py
cheutils/check.py
cheutils/common_base.py
cheutils/common_utils.py
cheutils/data_prep_support.py
cheutils/data_properties.py
cheutils/datasource_utils.py
cheutils/decorator_debug.py
cheutils/decorator_singleton.py
cheutils/decorator_timer.py
cheutils/exceptions.py
cheutils/loggers.py
cheutils/progress_tracking.py
cheutils/project_tree.py
cheutils/project_tree_handler.py
cheutils/properties_util.py
cheutils/setup.py
cheutils/sqlite_util.py
cheutils/target_encoder.py
cheutils/basic/__init__.py
cheutils/basic/transformations.py
cheutils/feature_generation/__init__.py
cheutils/feature_generation/cos_sine_features.py
cheutils/feature_generation/date_features.py
cheutils/feature_generation/extreme_states.py
cheutils/feature_generation/feature_trends.py
cheutils/feature_generation/geospatial_features.py
cheutils/feature_generation/interaction_features.py
cheutils/feature_generation/pct_change_features.py
cheutils/interceptor/__init__.py
cheutils/interceptor/drop_selected_cols.py
cheutils/interceptor/feature_intensity.py
cheutils/interceptor/feature_selection.py
cheutils/interceptor/interceptors.py
cheutils/interceptor/numeric_data.py
cheutils/interceptor/pipelineInterceptor.py
cheutils/ml/__init__.py
cheutils/ml/bayesian_search.py
cheutils/ml/evaluation_metrics.py
cheutils/ml/model_builder.py
cheutils/ml/model_properties.py
cheutils/ml/model_support.py
cheutils/ml/pipeline_details.py
cheutils/ml/setup.py
cheutils/ml/visualize.py
cheutils/timeseries/__init__.py
cheutils/timeseries/augmenters.py
cheutils-2.8.23.dist-info/licenses/LICENSE
cheutils-2.8.23.dist-info/METADATA
cheutils-2.8.23.dist-info/WHEEL
cheutils-2.8.23.dist-info/entry_points.txt
cheutils-2.8.23.dist-info/top_level.txt
cheutils-2.8.23.dist-info/RECORD
