Metadata-Version: 2.4
Name: cheutils
Version: 2.8.23
Summary: A set of basic reusable utilities and tools to facilitate quickly getting up and going on any machine learning project.
Author-email: Ferdinand Che <ferdinand.che@gmail.com>
Maintainer-email: Ferdinand Che <ferdinand.che@gmail.com>
Project-URL: Homepage, https://github.com/chewitty/cheutils
Project-URL: Issues, https://github.com/chewitty/cheutils/issues
Project-URL: Repository, https://github.com/chewitty/cheutils.git
Keywords: machine learning utilities,machine learning pipeline utilities,quick start machine learning,python project configuration,project configuration,python project properties files
Classifier: Programming Language :: Python :: 3
Classifier: License :: OSI Approved :: MIT License
Classifier: Operating System :: OS Independent
Requires-Python: >=3.9
License-File: LICENSE
Requires-Dist: numpy>=1.10
Requires-Dist: pandas
Requires-Dist: codetiming
Requires-Dist: tdqm
Requires-Dist: pytz
Requires-Dist: regex
Requires-Dist: typing
Requires-Dist: pydantic
Requires-Dist: inspect-it
Requires-Dist: jproperties
Requires-Dist: matplotlib
Requires-Dist: seaborn
Requires-Dist: scikit-learn
Requires-Dist: loguru
Requires-Dist: hyperopt
Requires-Dist: scikit-optimize
Requires-Dist: fast_ml
Requires-Dist: mlflow
Requires-Dist: dask
Requires-Dist: tsfresh
Requires-Dist: pingouin
Requires-Dist: pyodbc
Requires-Dist: psycopg2
Requires-Dist: pymysql
Requires-Dist: pymssql
Requires-Dist: mysql-connector-python
Requires-Dist: loky
Requires-Dist: geolib
Requires-Dist: category_encoders
Provides-Extra: datasource
Requires-Dist: dask[dataframe]; extra == "datasource"
Requires-Dist: psycopg2; extra == "datasource"
Requires-Dist: pyodbc; extra == "datasource"
Requires-Dist: pymysql; extra == "datasource"
Requires-Dist: mysqlclient; extra == "datasource"
Requires-Dist: pymssql; extra == "datasource"
Requires-Dist: mysql.connector; extra == "datasource"
Requires-Dist: sqlalchemy; extra == "datasource"
Provides-Extra: mlflow
Requires-Dist: mlflow; extra == "mlflow"
Dynamic: license-file
